{
  "AllTasks": {
    "100": {
      "id": 100,
      "status": "Open",
      "title": "Create button",
      "description": "This card is about of create button",
      "users": [
        {
          "id": 1,
          "name": "lio messi"
        },
        {
          "id": 2,
          "name": "sandra castro"
        },
        {
          "id": 4,
          "name": "sandra castro"
        },
        {
          "id": 7,
          "name": "v castro"
        }
      ]
    },
    "200": {
      "id": 200,
      "status": "Open",
      "title": "Research trello",
      "description": "Search good practices in trello app",
      "users": []
    },
    "300": {
      "id": 300,
      "status": "In Progress",
      "title": "Buy motorcycle",
      "description": "Buy yamaha rx4500",
      "users": [
        {
          "id": 1,
          "name": "par c"
        }
      ]
    },
    "400": {
      "id": 400,
      "status": "Done",
      "title": "Buy motorcycle",
      "description": "Buy yamaha rx4500",
      "users": [
        {
          "id": 1,
          "name": "diana caraballo"
        }
      ]
    }
  }
}
